[
  {"img":"img/p4788.jpg","name":"【酸甜开胃虾】","information":"<b>主要面食：</b>明虾、番茄酱、白糖、白醋、葱、姜、淀粉","price":"￥36.00","src":"#/xiangqing"},
  {"img":"img/p7933.jpg","name":"【酸甜开胃虾】","information":"<b>主要面食：</b>明虾、番茄酱、白糖、白醋、葱、姜、淀粉","price":"￥36.00","src":"#/xiangqing"},
  {"img":"img/p7818.jpg","name":"【酸甜开胃虾】","information":"<b>主要面食：</b>明虾、番茄酱、白糖、白醋、葱、姜、淀粉","price":"￥36.00","src":"#/xiangqing"},
  {"img":"img/p6611.jpg","name":"【酸甜开胃虾】","information":"<b>主要面食：</b>明虾、番茄酱、白糖、白醋、葱、姜、淀粉","price":"￥36.00","src":"#/xiangqing"},
  {"img":"img/p2679.jpg","name":"【酸甜开胃虾】","information":"<b>主要面食：</b>明虾、番茄酱、白糖、白醋、葱、姜、淀粉","price":"￥36.00","src":"#/xiangqing"},
  {"img":"img/p0281.jpg","name":"【酸甜开胃虾】","information":"<b>主要面食：</b>明虾、番茄酱、白糖、白醋、葱、姜、淀粉","price":"￥36.00","src":"#/xiangqing"}
]
